nlpearl/__init__.py
nlpearl/_helpers.py
nlpearl/account.py
nlpearl/call.py
nlpearl/inbound.py
nlpearl/outbound.py
nlpearl/pearl.py
nlpearl-1.0.6.dist-info/LICENSE
nlpearl-1.0.6.dist-info/METADATA
nlpearl-1.0.6.dist-info/WHEEL
nlpearl-1.0.6.dist-info/top_level.txt
nlpearl-1.0.6.dist-info/RECORD
