Metadata-Version: 2.1
Name: nlpearl
Version: 1.0.6
Summary: A Python wrapper for the NLPearl API
Home-page: https://github.com/Samueleons/NLPearl-API
Author: nlpearl
Author-email: support@nlpearl.ai
License: BSD-3-Clause
Project-URL: Source, https://github.com/Samueleons/NLPearl-API
Project-URL: Documentation, https://developers.nlpearl.ai
Project-URL: Homepage, https://www.nlpearl.ai
Keywords: nlpearl api wrapper client telephony automation python conversational-ai nlp call-handling
Classifier: Development Status :: 4 - Beta
Classifier: Intended Audience :: Developers
Classifier: Intended Audience :: Information Technology
Classifier: Topic :: Software Development :: Libraries :: Python Modules
Classifier: Topic :: Communications :: Telephony
Classifier: Topic :: Internet
Classifier: License :: OSI Approved :: BSD License
Classifier: Programming Language :: Python :: 3
Classifier: Programming Language :: Python :: 3.6
Classifier: Programming Language :: Python :: 3.7
Classifier: Programming Language :: Python :: 3.8
Classifier: Programming Language :: Python :: 3.9
Classifier: Programming Language :: Python :: 3.10
Classifier: Operating System :: OS Independent
Classifier: Natural Language :: English
Requires-Python: >=3.6, <4
License-File: LICENSE
Requires-Dist: requests
